MicroRegEx/Compiler.py
MicroRegEx/Compiler_test.py
MicroRegEx/PatternSyntaxError.py
MicroRegEx/Token.py
MicroRegEx/TokenToNFA.py
MicroRegEx/TokenToNFA_test.py
MicroRegEx/__init__.py
MicroRegEx/Automaton/DFA.py
MicroRegEx/Automaton/NFA.py
MicroRegEx/Automaton/NFA2DFA.py
MicroRegEx/Automaton/Status.py
MicroRegEx/Automaton/StatusSet.py
MicroRegEx/Automaton/__init__.py
MicroRegEx/Automaton/Minimal/Brzozowski.py
MicroRegEx/Automaton/Minimal/Brzozowski_test.py
MicroRegEx/Automaton/Minimal/Hopcroft.py
MicroRegEx/Automaton/Minimal/__init__.py
MicroRegEx/Automaton/SubsetConstruct/Offline.py
MicroRegEx/Automaton/SubsetConstruct/Online.py
MicroRegEx/Automaton/SubsetConstruct/Online_test.py
MicroRegEx/Automaton/SubsetConstruct/__init__.py
MicroRegEx/Lexer/Lexer.py
MicroRegEx/Lexer/Lexer_test.py
MicroRegEx/Lexer/__init__.py
MicroRegEx/Parser/Parser.py
MicroRegEx/Parser/Parser_test.py
MicroRegEx/Parser/RecursiveDescent.py
MicroRegEx/Parser/__init__.py
MicroRegEx-1.0.0.dist-info/LICENSE.md
MicroRegEx-1.0.0.dist-info/METADATA
MicroRegEx-1.0.0.dist-info/WHEEL
MicroRegEx-1.0.0.dist-info/top_level.txt
MicroRegEx-1.0.0.dist-info/RECORD
