Metadata-Version: 2.1
Name: MicroRegEx
Version: 1.0.0
Summary: A micro regular expression engine
Home-page: https://github.com/howl-anderson/MicroRegEx
Author: Xiaoquan Kong
Author-email: u1mail2me@gmail.com
License: MIT license
Platform: UNKNOWN
Classifier: Development Status :: 2 - Pre-Alpha
Classifier: Intended Audience :: Developers
Classifier: License :: OSI Approved :: MIT License
Classifier: Natural Language :: English
Classifier: Programming Language :: Python :: 2
Classifier: Programming Language :: Python :: 2.7
Classifier: Programming Language :: Python :: 3
Classifier: Programming Language :: Python :: 3.4
Classifier: Programming Language :: Python :: 3.5
Classifier: Programming Language :: Python :: 3.6
Requires-Dist: graphviz
